{
  "case_id": "CB-015",
  "title": "Indeterminate Evaluation Fails Closed",
  "category": "Admissibility Predicate",

  "glyph": {
    "glyph_id": "glyph.fail.015",
    "canonical_hash": "hash.fail.015",
    "pose_valid": true,
    "state_valid": true
  },

  "constraint_set": {
    "constraint_id": "constraints.v1",
    "admissible": null
  },

  "safety_predicate": {
    "safe": true
  },

  "artifact": {
    "present": true
  },

  "expected_result": "blocked",
  "expected_reason": "indeterminate_evaluation",

  "invariants": [
    "Admissibility is fail-closed under uncertainty"
  ]
}
