{
    "artifact":  {
                     "present":  true
                 },
    "expected_result":  "admitted",
    "title":  "Cross-Constitutional Baseline",
    "case_id":  "CE-020",
    "expected_reason":  "cross_constitutional_baseline",
    "glyph":  {
                  "canonical_hash":  "ce020-canonical-hash",
                  "glyph_id":  "CGO-CE-020"
              },
    "safety_predicate":  {
                             "safe":  true
                         },
    "constraint_set":  {
                           "admissible":  true
                       }
}
